acrome/__init__.py
acrome/controller.py
acrome/utils/__init__.py
acrome/utils/controller_fw_upgrade.py
acrome-0.3.2.dist-info/LICENSE
acrome-0.3.2.dist-info/METADATA
acrome-0.3.2.dist-info/WHEEL
acrome-0.3.2.dist-info/top_level.txt
acrome-0.3.2.dist-info/RECORD
