Metadata-Version: 2.1
Name: acrome
Version: 0.3.2
Summary: Hardware abstraction library for Acrome Robotics products
Home-page: https://github.com/acrome-robotics/python-library
Author: Umut Ediz
Author-email: umutediz@acrome.net
Project-URL: Bug Tracker, https://github.com/acrome-robotics/python-library/issues
Classifier: Programming Language :: Python :: 3
Classifier: License :: OSI Approved :: MIT License
Classifier: Operating System :: OS Independent
Requires-Python: >=3.7
License-File: LICENSE
Requires-Dist: pyserial
Requires-Dist: crccheck
Requires-Dist: stm32loader ==0.5.1
Requires-Dist: requests
Requires-Dist: packaging
